[{"bossmenu":{"x":-50.28137969970703,"z":25.43904304504394,"y":-1106.996826171875},"shops":[{"coords":{"x":500.7664184570313,"z":25.16863250732422,"y":-1963.7596435546876},"items":[{"itemName":"kq_ecstasy","price":100},{"itemName":"emerald_ring","price":100},{"itemName":"wallet","price":100},{"itemName":"vape","price":100},{"itemName":"pizza_box","price":100},{"itemName":"huntingbrochure","price":100},{"itemName":"spray_remover","price":100},{"itemName":"finger_scanner","price":100},{"itemName":"coca_blend","price":100}],"id":"shop_police_0_3191","label":"Obchod"}],"peds":[{"coords":{"x":-55.17199325561523,"z":26.43776130676269,"y":-1106.0743408203126},"heading":151.0977325439453,"label":"a_m_m_acult_01","model":"a_m_m_acult_01"},{"coords":{"x":500.4291687011719,"z":24.9851016998291,"y":-1963.8092041015626},"heading":124.46617889404296,"label":"a_m_m_acult_01","model":"a_m_m_acult_01"}],"craftings":[{"coords":{"x":-50.59649276733398,"z":26.37905311584472,"y":-1104.2711181640626},"items":[{"itemCount":1,"itemName":"ruby","ingedience":[{"itemCount":1,"itemName":"jidelni-listek"},{"itemCount":1,"itemName":"clothes"},{"itemCount":1,"itemName":"t1ger_brakepad"}]},{"itemCount":1,"itemName":"scratch_ticket","ingedience":[{"itemCount":1,"itemName":"bottle_water"}]}],"id":"police0_795","label":"Crafting main"}],"stashes":[{"slots":50,"weight":100000,"label":"Storage room","job":true,"coords":{"x":-52.90103912353515,"z":25.4373779296875,"y":-1102.9781494140626},"id":"police0_7361"}],"blips":[{"color":17,"id":"blip_police_1775037295761","sprite":1,"label":"Police test","jobOnly":false,"coords":{"x":180.67088317871098,"z":29.276704788208,"y":-1013.7802734375},"scale":0.4}],"coords":{"x":10.94440746307373,"z":38.15372848510742,"y":-1069.039794921875},"alarm":{"x":-49.40534210205078,"z":25.4373779296875,"y":-1105.5501708984376},"register":{"x":-48.83920288085937,"z":26.39266204833984,"y":-1104.761474609375},"props":[{"coords":{"x":188.0982666015625,"z":28.26938247680664,"y":-1016.297119140625},"rotation":{"x":0,"z":-19.9999942779541,"y":0},"id":"prop_police_1775037406141","model":"v_corp_cd_rectable"}],"balance":4400,"job":"police","area":50,"label":"Police test"}]